aws_secret_cdk/__init__.py
aws_secret_cdk/base_secret.py
aws_secret_cdk/base_secret_rotation.py
aws_secret_cdk/vpc_parameters.py
aws_secret_cdk/aurora_mysql_multiuser_user/__init__.py
aws_secret_cdk/aurora_mysql_multiuser_user/secret.py
aws_secret_cdk/aurora_mysql_multiuser_user/secret_rotation.py
aws_secret_cdk/aurora_mysql_multiuser_user/package_src/__init__.py
aws_secret_cdk/aurora_mysql_single_user/__init__.py
aws_secret_cdk/aurora_mysql_single_user/secret.py
aws_secret_cdk/aurora_mysql_single_user/secret_rotation.py
aws_secret_cdk/aurora_mysql_single_user/package_src/__init__.py
aws_secret_cdk/aurora_mysql_single_user/package_src/lambda_function.py
aws_secret_cdk/aurora_mysql_single_user/package_src/pymysql/__init__.py
aws_secret_cdk/aurora_mysql_single_user/package_src/pymysql/_auth.py
aws_secret_cdk/aurora_mysql_single_user/package_src/pymysql/_compat.py
aws_secret_cdk/aurora_mysql_single_user/package_src/pymysql/_socketio.py
aws_secret_cdk/aurora_mysql_single_user/package_src/pymysql/charset.py
aws_secret_cdk/aurora_mysql_single_user/package_src/pymysql/connections.py
aws_secret_cdk/aurora_mysql_single_user/package_src/pymysql/converters.py
aws_secret_cdk/aurora_mysql_single_user/package_src/pymysql/cursors.py
aws_secret_cdk/aurora_mysql_single_user/package_src/pymysql/err.py
aws_secret_cdk/aurora_mysql_single_user/package_src/pymysql/optionfile.py
aws_secret_cdk/aurora_mysql_single_user/package_src/pymysql/protocol.py
aws_secret_cdk/aurora_mysql_single_user/package_src/pymysql/times.py
aws_secret_cdk/aurora_mysql_single_user/package_src/pymysql/util.py
aws_secret_cdk/aurora_mysql_single_user/package_src/pymysql/constants/CLIENT.py
aws_secret_cdk/aurora_mysql_single_user/package_src/pymysql/constants/COMMAND.py
aws_secret_cdk/aurora_mysql_single_user/package_src/pymysql/constants/CR.py
aws_secret_cdk/aurora_mysql_single_user/package_src/pymysql/constants/ER.py
aws_secret_cdk/aurora_mysql_single_user/package_src/pymysql/constants/FIELD_TYPE.py
aws_secret_cdk-5.3.0.dist-info/LICENSE.txt
aws_secret_cdk-5.3.0.dist-info/METADATA
aws_secret_cdk-5.3.0.dist-info/WHEEL
aws_secret_cdk-5.3.0.dist-info/top_level.txt
aws_secret_cdk-5.3.0.dist-info/RECORD
