Metadata-Version: 2.1
Name: aws-secret-cdk
Version: 5.3.0
Summary: Package to create a SecretsManager's secret with auto rotation.
Home-page: https://github.com/idenfy/AwsSecretCdk
Author: Laimonas Sutkus
Author-email: laimonas@idenfy.com,laimonas.sutkus@gmail.com
License: GNU GENERAL PUBLIC LICENSE Version 3
Keywords: AWS CDK CloudFormation SecretsManager Infrastructure Cloud DevOps
Platform: UNKNOWN
Classifier: Programming Language :: Python :: 3
Classifier: Programming Language :: Python :: 3.5
Classifier: Programming Language :: Python :: 3.6
Classifier: Programming Language :: Python :: 3.7
Classifier: Programming Language :: Python :: 3.8
Classifier: Operating System :: OS Independent
Requires-Dist: aws-cdk.core (<2.0.0,>=1.60.0)
Requires-Dist: aws-cdk.aws-iam (<2.0.0,>=1.60.0)
Requires-Dist: aws-cdk.aws-ec2 (<2.0.0,>=1.60.0)
Requires-Dist: aws-cdk.aws-lambda (<2.0.0,>=1.60.0)
Requires-Dist: aws-cdk.aws-rds (<2.0.0,>=1.60.0)
Requires-Dist: aws-cdk.aws-secretsmanager (<2.0.0,>=1.60.0)
Requires-Dist: aws-cdk.aws-s3-deployment (<2.0.0,>=1.60.0)
Requires-Dist: aws-lambda (<3.0.0,>=2.1.2)
